{
  "ExportTimeUTC": "2023-02-18T18:32:11.8597603Z",
  "Name": "Execution_Shank",
  "Length": 2.0,
  "Bounds": {
    "x": -1.07775736,
    "y": -1.0863179,
    "width": 3.55595684,
    "height": 2.53748
  },
  "Events": [
    {
      "Time": 0.45,
      "Data": "DamageEffect;1;0,0,0"
    },
    {
      "Time": 0.75,
      "Data": "DamageEffect;1;0,0,0"
    },
    {
      "Time": 2.0,
      "Data": "KillPawn;0;1;Heart;Stab;AAM_Execution_Stab;True"
    }
  ],
  "Parts": [
    {
      "ID": 19430,
      "Path": "PawnAHolding",
      "Curves": {
        "Transform.localEulerAnglesRaw.x": {
          "Keyframes": [
            {
              "inWeight": 0.333333343,
              "outWeight": 0.333333343,
              "tangentMode": 136
            },
            {
              "time": 0.316666663,
              "inWeight": 0.333333343,
              "outWeight": 0.333333343,
              "tangentMode": 136
            },
            {
              "time": 0.45,
              "inWeight": 0.333333343,
              "outWeight": 0.333333343,
              "tangentMode": 136
            },
            {
              "time": 0.566666663,
              "inWeight": 0.333333343,
              "outWeight": 0.333333343,
              "tangentMode": 136
            },
            {
              "time": 0.716666639,
              "inWeight": 0.333333343,
              "outWeight": 0.333333343,
              "tangentMode": 136
            },
            {
              "time": 0.8,
              "inWeight": 0.333333343,
              "outWeight": 0.333333343,
              "tangentMode": 136
            },
            {
              "time": 1.11666667,
              "inWeight": 0.333333343,
              "outWeight": 0.333333343,
              "tangentMode": 136
            },
            {
              "time": 1.33333337,
              "inWeight": 0.333333343,
              "outWeight": 0.333333343,
              "tangentMode": 136
            },
            {
              "time": 1.41666663,
              "inWeight": 0.333333343,
              "outWeight": 0.333333343,
              "tangentMode": 136
            },
            {
              "time": 1.51666665,
              "inWeight": 0.333333343,
              "outWeight": 0.333333343,
              "tangentMode": 136
            },
            {
              "time": 1.65,
              "inWeight": 0.333333343,
              "outWeight": 0.333333343,
              "tangentMode": 136
            },
            {
              "time": 2.0,
              "inWeight": 0.333333343,
              "outWeight": 0.333333343,
              "tangentMode": 136
            }
          ],
          "PreWrapMode": 8,
          "PostWrapMode": 8
        },
        "Transform.localEulerAnglesRaw.y": {
          "Keyframes": [
            {
              "value": 12.678,
              "inWeight": 0.333333343,
              "outWeight": 0.333333343,
              "tangentMode": 136
            },
            {
              "time": 0.316666663,
              "value": 11.265,
              "inTangent": -12.5600014,
              "outTangent": -12.5600014,
              "inWeight": 0.333333343,
              "outWeight": 0.333333343,
              "tangentMode": 136
            },
            {
              "time": 0.45,
              "value": -23.472,
              "inWeight": 0.333333343,
              "outWeight": 0.333333343,
              "tangentMode": 136
            },
            {
              "time": 0.566666663,
              "value": -23.472,
              "inWeight": 0.333333343,
              "outWeight": 0.333333343,
              "tangentMode": 136
            },
            {
              "time": 0.716666639,
              "value": -13.583,
              "inWeight": 0.333333343,
              "outWeight": 0.333333343,
              "tangentMode": 136
            },
            {
              "time": 0.8,
              "value": -33.165,
              "inWeight": 0.333333343,
              "outWeight": 0.333333343,
              "tangentMode": 136
            },
            {
              "time": 1.11666667,
              "value": -23.666,
              "inWeight": 0.333333343,
              "outWeight": 0.333333343,
              "tangentMode": 136
            },
            {
              "time": 1.33333337,
              "value": -120.902,
              "inWeight": 0.333333343,
              "outWeight": 0.333333343,
              "tangentMode": 136
            },
            {
              "time": 1.41666663,
              "value": -120.902,
              "inWeight": 0.333333343,
              "outWeight": 0.333333343,
              "tangentMode": 136
            },
            {
              "time": 1.51666665,
              "value": -120.902,
              "inWeight": 0.333333343,
              "outWeight": 0.333333343,
              "tangentMode": 136
            },
            {
              "time": 1.65,
              "value": -102.115,
              "inTangent": 155.478638,
              "outTangent": 155.478638,
              "inWeight": 0.333333343,
              "outWeight": 0.333333343,
              "tangentMode": 136
            },
            {
              "time": 2.0,
              "value": -35.649,
              "inWeight": 0.333333343,
              "outWeight": 0.333333343,
              "tangentMode": 136
            }
          ],
          "PreWrapMode": 8,
          "PostWrapMode": 8
        },
        "Transform.localEulerAnglesRaw.z": {
          "Keyframes": [
            {
              "inWeight": 0.333333343,
              "outWeight": 0.333333343,
              "tangentMode": 136
            },
            {
              "time": 0.316666663,
              "inWeight": 0.333333343,
              "outWeight": 0.333333343,
              "tangentMode": 136
            },
            {
              "time": 0.45,
              "inWeight": 0.333333343,
              "outWeight": 0.333333343,
              "tangentMode": 136
            },
            {
              "time": 0.566666663,
              "inWeight": 0.333333343,
              "outWeight": 0.333333343,
              "tangentMode": 136
            },
            {
              "time": 0.716666639,
              "inWeight": 0.333333343,
              "outWeight": 0.333333343,
              "tangentMode": 136
            },
            {
              "time": 0.8,
              "inWeight": 0.333333343,
              "outWeight": 0.333333343,
              "tangentMode": 136
            },
            {
              "time": 1.11666667,
              "inWeight": 0.333333343,
              "outWeight": 0.333333343,
              "tangentMode": 136
            },
            {
              "time": 1.33333337,
              "inWeight": 0.333333343,
              "outWeight": 0.333333343,
              "tangentMode": 136
            },
            {
              "time": 1.41666663,
              "inWeight": 0.333333343,
              "outWeight": 0.333333343,
              "tangentMode": 136
            },
            {
              "time": 1.51666665,
              "inWeight": 0.333333343,
              "outWeight": 0.333333343,
              "tangentMode": 136
            },
            {
              "time": 1.65,
              "inWeight": 0.333333343,
              "outWeight": 0.333333343,
              "tangentMode": 136
            },
            {
              "time": 2.0,
              "inWeight": 0.333333343,
              "outWeight": 0.333333343,
              "tangentMode": 136
            }
          ],
          "PreWrapMode": 8,
          "PostWrapMode": 8
        },
        "Transform.m_LocalPosition.x": {
          "Keyframes": [
            {
              "value": -0.193,
              "inWeight": 0.333333343,
              "outWeight": 0.333333343,
              "tangentMode": 136
            },
            {
              "time": 0.216666669,
              "value": 0.1865,
              "inTangent": 1.06736827,
              "outTangent": 1.06736827,
              "inWeight": 0.333333343,
              "outWeight": 0.333333343,
              "tangentMode": 136
            },
            {
              "time": 0.316666663,
              "value": 0.271,
              "inTangent": 1.44857156,
              "outTangent": 1.44857156,
              "inWeight": 0.333333343,
              "outWeight": 0.333333343,
              "tangentMode": 136
            },
            {
              "time": 0.45,
              "value": 0.674,
              "inTangent": 0.543999553,
              "outTangent": 0.543999553,
              "inWeight": 0.333333343,
              "outWeight": 0.333333343,
              "tangentMode": 136
            },
            {
              "time": 0.566666663,
              "value": 0.708,
              "inWeight": 0.333333343,
              "outWeight": 0.333333343,
              "tangentMode": 136
            },
            {
              "time": 0.65,
              "value": 0.42,
              "inTangent": -1.67999959,
              "outTangent": -1.67999959,
              "inWeight": 0.333333343,
              "outWeight": 0.333333343,
              "tangentMode": 136
            },
            {
              "time": 0.716666639,
              "value": 0.357,
              "inWeight": 0.333333343,
              "outWeight": 0.333333343,
              "tangentMode": 136
            },
            {
              "time": 0.8,
              "value": 0.718,
              "inWeight": 0.333333343,
              "outWeight": 0.333333343,
              "tangentMode": 136
            },
            {
              "time": 0.933333337,
              "value": 0.718,
              "inWeight": 0.333333343,
              "outWeight": 0.333333343,
              "tangentMode": 136
            },
            {
              "time": 1.05,
              "value": 0.377,
              "inTangent": -1.9111433,
              "outTangent": -1.9111433,
              "inWeight": 0.333333343,
              "outWeight": 0.333333343,
              "tangentMode": 136
            },
            {
              "time": 1.18333328,
              "value": 0.2402143,
              "inTangent": -1.48941123,
              "outTangent": -1.48941123,
              "inWeight": 0.333333343,
              "outWeight": 0.333333343,
              "tangentMode": 136
            },
            {
              "time": 1.33333337,
              "value": -0.045,
              "inTangent": -1.78377545,
              "outTangent": -1.78377545,
              "inWeight": 0.333333343,
              "outWeight": 0.333333343,
              "tangentMode": 136
            },
            {
              "time": 1.41666663,
              "value": -0.176,
              "inWeight": 0.333333343,
              "outWeight": 0.333333343,
              "tangentMode": 136
            },
            {
              "time": 1.4666667,
              "value": 0.567,
              "inWeight": 0.333333343,
              "outWeight": 0.333333343,
              "tangentMode": 136
            },
            {
              "time": 1.51666665,
              "value": 0.567,
              "inWeight": 0.333333343,
              "outWeight": 0.333333343,
              "tangentMode": 136
            },
            {
              "time": 1.65,
              "value": 0.762,
              "inWeight": 0.333333343,
              "outWeight": 0.333333343,
              "tangentMode": 136
            },
            {
              "time": 2.0,
              "value": 0.27,
              "inWeight": 0.333333343,
              "outWeight": 0.333333343,
              "tangentMode": 136
            }
          ],
          "PreWrapMode": 8,
          "PostWrapMode": 8
        },
        "Transform.m_LocalPosition.y": {
          "Keyframes": [
            {
              "value": 0.2,
              "inWeight": 0.333333343,
              "outWeight": 0.333333343,
              "tangentMode": 136
            },
            {
              "time": 0.216666669,
              "value": 0.2,
              "inWeight": 0.333333343,
              "outWeight": 0.333333343,
              "tangentMode": 136
            },
            {
              "time": 0.316666663,
              "value": 0.2,
              "inWeight": 0.333333343,
              "outWeight": 0.333333343,
              "tangentMode": 136
            },
            {
              "time": 0.45,
              "value": 0.2,
              "inWeight": 0.333333343,
              "outWeight": 0.333333343,
              "tangentMode": 136
            },
            {
              "time": 0.566666663,
              "value": 0.2,
              "inWeight": 0.333333343,
              "outWeight": 0.333333343,
              "tangentMode": 136
            },
            {
              "time": 0.65,
              "value": 0.2,
              "inWeight": 0.333333343,
              "outWeight": 0.333333343,
              "tangentMode": 136
            },
            {
              "time": 0.716666639,
              "value": 0.2,
              "inWeight": 0.333333343,
              "outWeight": 0.333333343,
              "tangentMode": 136
            },
            {
              "time": 0.8,
              "value": 0.2,
              "inWeight": 0.333333343,
              "outWeight": 0.333333343,
              "tangentMode": 136
            },
            {
              "time": 0.933333337,
              "value": 0.2,
              "inWeight": 0.333333343,
              "outWeight": 0.333333343,
              "tangentMode": 136
            },
            {
              "time": 1.05,
              "value": 0.2,
              "inWeight": 0.333333343,
              "outWeight": 0.333333343,
              "tangentMode": 136
            },
            {
              "time": 1.18333328,
              "value": 0.2,
              "inWeight": 0.333333343,
              "outWeight": 0.333333343,
              "tangentMode": 136
            },
            {
              "time": 1.33333337,
              "value": 0.2,
              "inWeight": 0.333333343,
              "outWeight": 0.333333343,
              "tangentMode": 136
            },
            {
              "time": 1.41666663,
              "value": 0.2,
              "inWeight": 0.333333343,
              "outWeight": 0.333333343,
              "tangentMode": 136
            },
            {
              "time": 1.4666667,
              "value": 0.2,
              "inWeight": 0.333333343,
              "outWeight": 0.333333343,
              "tangentMode": 136
            },
            {
              "time": 1.51666665,
              "value": 0.2,
              "inWeight": 0.333333343,
              "outWeight": 0.333333343,
              "tangentMode": 136
            },
            {
              "time": 1.65,
              "value": 0.2,
              "inWeight": 0.333333343,
              "outWeight": 0.333333343,
              "tangentMode": 136
            },
            {
              "time": 2.0,
              "value": 0.2,
              "inWeight": 0.333333343,
              "outWeight": 0.333333343,
              "tangentMode": 136
            }
          ],
          "PreWrapMode": 8,
          "PostWrapMode": 8
        },
        "Transform.m_LocalPosition.z": {
          "Keyframes": [
            {
              "value": -0.208,
              "inWeight": 0.333333343,
              "outWeight": 0.333333343,
              "tangentMode": 136
            },
            {
              "time": 0.216666669,
              "value": -0.24,
              "inTangent": -0.179999948,
              "outTangent": -0.179999948,
              "inWeight": 0.333333343,
              "outWeight": 0.333333343,
              "tangentMode": 136
            },
            {
              "time": 0.316666663,
              "value": -0.265,
              "inWeight": 0.333333343,
              "outWeight": 0.333333343,
              "tangentMode": 136
            },
            {
              "time": 0.45,
              "value": -0.242,
              "inWeight": 0.333333343,
              "outWeight": 0.333333343,
              "tangentMode": 136
            },
            {
              "time": 0.566666663,
              "value": -0.242,
              "inWeight": 0.333333343,
              "outWeight": 0.333333343,
              "tangentMode": 136
            },
            {
              "time": 0.65,
              "value": -0.337,
              "inWeight": 0.333333343,
              "outWeight": 0.333333343,
              "tangentMode": 136
            },
            {
              "time": 0.716666639,
              "value": -0.334,
              "inTangent": 0.08000054,
              "outTangent": 0.08000054,
              "inWeight": 0.333333343,
              "outWeight": 0.333333343,
              "tangentMode": 136
            },
            {
              "time": 0.8,
              "value": -0.144,
              "inWeight": 0.333333343,
              "outWeight": 0.333333343,
              "tangentMode": 136
            },
            {
              "time": 0.933333337,
              "value": -0.144,
              "inWeight": 0.333333343,
              "outWeight": 0.333333343,
              "tangentMode": 136
            },
            {
              "time": 1.05,
              "value": -0.293,
              "inWeight": 0.333333343,
              "outWeight": 0.333333343,
              "tangentMode": 136
            },
            {
              "time": 1.18333328,
              "value": -0.218,
              "inTangent": 1.05176437,
              "outTangent": 1.05176437,
              "inWeight": 0.333333343,
              "outWeight": 0.333333343,
              "tangentMode": 136
            },
            {
              "time": 1.33333337,
              "value": 0.005,
              "inTangent": 0.9942855,
              "outTangent": 0.9942855,
              "inWeight": 0.333333343,
              "outWeight": 0.333333343,
              "tangentMode": 136
            },
            {
              "time": 1.41666663,
              "value": 0.063,
              "inTangent": 1.74000013,
              "outTangent": 1.74000013,
              "inWeight": 0.333333343,
              "outWeight": 0.333333343,
              "tangentMode": 136
            },
            {
              "time": 1.4666667,
              "value": 0.284,
              "inWeight": 0.333333343,
              "outWeight": 0.333333343,
              "tangentMode": 136
            },
            {
              "time": 1.51666665,
              "value": 0.284,
              "inWeight": 0.333333343,
              "outWeight": 0.333333343,
              "tangentMode": 136
            },
            {
              "time": 1.65,
              "value": 0.132,
              "inTangent": -1.04482758,
              "outTangent": -1.04482758,
              "inWeight": 0.333333343,
              "outWeight": 0.333333343,
              "tangentMode": 136
            },
            {
              "time": 2.0,
              "value": -0.221,
              "inWeight": 0.333333343,
              "outWeight": 0.333333343,
              "tangentMode": 136
            }
          ],
          "PreWrapMode": 8,
          "PostWrapMode": 8
        }
      },
      "DefaultValues": {
        "GameObject.m_IsActive": 1.0,
        "Transform.m_LocalScale.x": 1.0,
        "Transform.m_LocalScale.y": 1.0,
        "Transform.m_LocalScale.z": 1.0,
        "AnimatedPart.DataA": 0.0,
        "AnimatedPart.DataB": 0.0,
        "AnimatedPart.DataC": 0.0,
        "AnimatedPart.Tint.r": 0.0,
        "AnimatedPart.Tint.g": 0.0,
        "AnimatedPart.Tint.b": 0.0,
        "AnimatedPart.Tint.a": 0.0,
        "AnimatedPart.FlipX": 0.0,
        "AnimatedPart.FlipY": 0.0,
        "AnimatedPart.SplitDrawMode": 0.0,
        "AnimatedPart.FrameIndex": 0.0,
        "PawnBody.Direction": 0.0
      },
      "SweepPaths": []
    },
    {
      "ID": 19452,
      "Path": "BodyA",
      "CustomName": "BodyA",
      "Curves": {
        "Transform.m_LocalPosition.x": {
          "Keyframes": [
            {
              "inWeight": 0.333333343,
              "outWeight": 0.333333343,
              "tangentMode": 136
            },
            {
              "time": 0.216666669,
              "value": 0.118499994,
              "inTangent": 0.5266667,
              "outTangent": 0.5266667,
              "inWeight": 0.333333343,
              "outWeight": 0.333333343,
              "tangentMode": 136
            },
            {
              "time": 0.45,
              "value": 0.237,
              "inTangent": 0.388571024,
              "outTangent": 0.388571024,
              "inWeight": 0.333333343,
              "outWeight": 0.333333343,
              "tangentMode": 136
            },
            {
              "time": 0.566666663,
              "value": 0.270999968,
              "inWeight": 0.333333343,
              "outWeight": 0.333333343,
              "tangentMode": 136
            },
            {
              "time": 0.65,
              "value": 0.202999949,
              "inTangent": -0.426665217,
              "outTangent": -0.426665217,
              "inWeight": 0.333333343,
              "outWeight": 0.333333343,
              "tangentMode": 136
            },
            {
              "time": 0.716666639,
              "value": 0.187,
              "inWeight": 0.333333343,
              "outWeight": 0.333333343,
              "tangentMode": 136
            },
            {
              "time": 0.8,
              "value": 0.216,
              "inTangent": 0.272307783,
              "outTangent": 0.272307783,
              "inWeight": 0.333333343,
              "outWeight": 0.333333343,
              "tangentMode": 136
            },
            {
              "time": 0.933333337,
              "value": 0.246000037,
              "inWeight": 0.333333343,
              "outWeight": 0.333333343,
              "tangentMode": 136
            },
            {
              "time": 1.05,
              "value": 0.059,
              "inTangent": -1.25400054,
              "outTangent": -1.25400054,
              "inWeight": 0.333333343,
              "outWeight": 0.333333343,
              "tangentMode": 136
            },
            {
              "time": 1.18333328,
              "value": -0.0674999952,
              "inTangent": -0.698823333,
              "outTangent": -0.698823333,
              "inWeight": 0.333333343,
              "outWeight": 0.333333343,
              "tangentMode": 136
            },
            {
              "time": 1.33333337,
              "value": -0.139,
              "inTangent": -0.308571517,
              "outTangent": -0.308571517,
              "inWeight": 0.333333343,
              "outWeight": 0.333333343,
              "tangentMode": 136
            },
            {
              "time": 1.41666663,
              "value": -0.157,
              "inWeight": 0.333333343,
              "outWeight": 0.333333343,
              "tangentMode": 136
            },
            {
              "time": 1.4666667,
              "value": 0.012,
              "inWeight": 0.333333343,
              "outWeight": 0.333333343,
              "tangentMode": 136
            },
            {
              "time": 1.51666665,
              "value": 0.012,
              "inWeight": 0.333333343,
              "outWeight": 0.333333343,
              "tangentMode": 136
            },
            {
              "time": 1.65,
              "value": 0.167,
              "inWeight": 0.333333343,
              "outWeight": 0.333333343,
              "tangentMode": 136
            },
            {
              "time": 2.0,
              "inWeight": 0.333333343,
              "outWeight": 0.333333343,
              "tangentMode": 136
            }
          ],
          "PreWrapMode": 8,
          "PostWrapMode": 8
        },
        "Transform.m_LocalPosition.y": {
          "Keyframes": [
            {
              "inWeight": 0.333333343,
              "outWeight": 0.333333343,
              "tangentMode": 136
            },
            {
              "time": 0.216666669,
              "inWeight": 0.333333343,
              "outWeight": 0.333333343,
              "tangentMode": 136
            },
            {
              "time": 0.45,
              "inWeight": 0.333333343,
              "outWeight": 0.333333343,
              "tangentMode": 136
            },
            {
              "time": 0.566666663,
              "inWeight": 0.333333343,
              "outWeight": 0.333333343,
              "tangentMode": 136
            },
            {
              "time": 0.65,
              "inWeight": 0.333333343,
              "outWeight": 0.333333343,
              "tangentMode": 136
            },
            {
              "time": 0.716666639,
              "inWeight": 0.333333343,
              "outWeight": 0.333333343,
              "tangentMode": 136
            },
            {
              "time": 0.8,
              "inWeight": 0.333333343,
              "outWeight": 0.333333343,
              "tangentMode": 136
            },
            {
              "time": 0.933333337,
              "inWeight": 0.333333343,
              "outWeight": 0.333333343,
              "tangentMode": 136
            },
            {
              "time": 1.05,
              "inWeight": 0.333333343,
              "outWeight": 0.333333343,
              "tangentMode": 136
            },
            {
              "time": 1.18333328,
              "inWeight": 0.333333343,
              "outWeight": 0.333333343,
              "tangentMode": 136
            },
            {
              "time": 1.33333337,
              "inWeight": 0.333333343,
              "outWeight": 0.333333343,
              "tangentMode": 136
            },
            {
              "time": 1.41666663,
              "inWeight": 0.333333343,
              "outWeight": 0.333333343,
              "tangentMode": 136
            },
            {
              "time": 1.4666667,
              "inWeight": 0.333333343,
              "outWeight": 0.333333343,
              "tangentMode": 136
            },
            {
              "time": 1.51666665,
              "inWeight": 0.333333343,
              "outWeight": 0.333333343,
              "tangentMode": 136
            },
            {
              "time": 1.65,
              "inWeight": 0.333333343,
              "outWeight": 0.333333343,
              "tangentMode": 136
            },
            {
              "time": 2.0,
              "inWeight": 0.333333343,
              "outWeight": 0.333333343,
              "tangentMode": 136
            }
          ],
          "PreWrapMode": 8,
          "PostWrapMode": 8
        },
        "Transform.m_LocalPosition.z": {
          "Keyframes": [
            {
              "inWeight": 0.333333343,
              "outWeight": 0.333333343,
              "tangentMode": 136
            },
            {
              "time": 0.216666669,
              "value": 0.06300001,
              "inWeight": 0.333333343,
              "outWeight": 0.333333343,
              "tangentMode": 136
            },
            {
              "time": 0.45,
              "inWeight": 0.333333343,
              "outWeight": 0.333333343,
              "tangentMode": 136
            },
            {
              "time": 0.566666663,
              "inWeight": 0.333333343,
              "outWeight": 0.333333343,
              "tangentMode": 136
            },
            {
              "time": 0.65,
              "inWeight": 0.333333343,
              "outWeight": 0.333333343,
              "tangentMode": 136
            },
            {
              "time": 0.716666639,
              "value": -0.001,
              "inWeight": 0.333333343,
              "outWeight": 0.333333343,
              "tangentMode": 136
            },
            {
              "time": 0.8,
              "value": -0.001,
              "inWeight": 0.333333343,
              "outWeight": 0.333333343,
              "tangentMode": 136
            },
            {
              "time": 0.933333337,
              "value": 0.001999991,
              "inTangent": 0.04799987,
              "outTangent": 0.04799987,
              "inWeight": 0.333333343,
              "outWeight": 0.333333343,
              "tangentMode": 136
            },
            {
              "time": 1.05,
              "value": 0.028,
              "inTangent": 0.416000247,
              "outTangent": 0.416000247,
              "inWeight": 0.333333343,
              "outWeight": 0.333333343,
              "tangentMode": 136
            },
            {
              "time": 1.18333328,
              "value": 0.10842859,
              "inWeight": 0.333333343,
              "outWeight": 0.333333343,
              "tangentMode": 136
            },
            {
              "time": 1.33333337,
              "value": 0.07800001,
              "inWeight": 0.333333343,
              "outWeight": 0.333333343,
              "tangentMode": 136
            },
            {
              "time": 1.41666663,
              "value": 0.08300001,
              "inTangent": 0.1500001,
              "outTangent": 0.1500001,
              "inWeight": 0.333333343,
              "outWeight": 0.333333343,
              "tangentMode": 136
            },
            {
              "time": 1.4666667,
              "value": 0.125,
              "inWeight": 0.333333343,
              "outWeight": 0.333333343,
              "tangentMode": 136
            },
            {
              "time": 1.51666665,
              "value": 0.125,
              "inWeight": 0.333333343,
              "outWeight": 0.333333343,
              "tangentMode": 136
            },
            {
              "time": 1.65,
              "value": 0.054,
              "inTangent": -0.258620679,
              "outTangent": -0.258620679,
              "inWeight": 0.333333343,
              "outWeight": 0.333333343,
              "tangentMode": 136
            },
            {
              "time": 2.0,
              "inWeight": 0.333333343,
              "outWeight": 0.333333343,
              "tangentMode": 136
            }
          ],
          "PreWrapMode": 8,
          "PostWrapMode": 8
        },
        "Transform.localEulerAnglesRaw.x": {
          "Keyframes": [
            {
              "inWeight": 0.333333343,
              "outWeight": 0.333333343,
              "tangentMode": 136
            },
            {
              "time": 0.316666663,
              "inWeight": 0.333333343,
              "outWeight": 0.333333343,
              "tangentMode": 136
            },
            {
              "time": 0.45,
              "inWeight": 0.333333343,
              "outWeight": 0.333333343,
              "tangentMode": 136
            },
            {
              "time": 0.566666663,
              "inWeight": 0.333333343,
              "outWeight": 0.333333343,
              "tangentMode": 136
            },
            {
              "time": 0.65,
              "inWeight": 0.333333343,
              "outWeight": 0.333333343,
              "tangentMode": 136
            },
            {
              "time": 0.716666639,
              "inWeight": 0.333333343,
              "outWeight": 0.333333343,
              "tangentMode": 136
            },
            {
              "time": 0.8,
              "inWeight": 0.333333343,
              "outWeight": 0.333333343,
              "tangentMode": 136
            },
            {
              "time": 1.05,
              "inWeight": 0.333333343,
              "outWeight": 0.333333343,
              "tangentMode": 136
            },
            {
              "time": 1.33333337,
              "inWeight": 0.333333343,
              "outWeight": 0.333333343,
              "tangentMode": 136
            },
            {
              "time": 1.41666663,
              "inWeight": 0.333333343,
              "outWeight": 0.333333343,
              "tangentMode": 136
            },
            {
              "time": 1.4666667,
              "inWeight": 0.333333343,
              "outWeight": 0.333333343,
              "tangentMode": 136
            },
            {
              "time": 1.51666665,
              "inWeight": 0.333333343,
              "outWeight": 0.333333343,
              "tangentMode": 136
            },
            {
              "time": 1.65,
              "inWeight": 0.333333343,
              "outWeight": 0.333333343,
              "tangentMode": 136
            },
            {
              "time": 2.0,
              "inWeight": 0.333333343,
              "outWeight": 0.333333343,
              "tangentMode": 136
            }
          ],
          "PreWrapMode": 8,
          "PostWrapMode": 8
        },
        "Transform.localEulerAnglesRaw.y": {
          "Keyframes": [
            {
              "inWeight": 0.333333343,
              "outWeight": 0.333333343,
              "tangentMode": 136
            },
            {
              "time": 0.316666663,
              "value": 1.081,
              "inWeight": 0.333333343,
              "outWeight": 0.333333343,
              "tangentMode": 136
            },
            {
              "time": 0.45,
              "value": -9.983,
              "inWeight": 0.333333343,
              "outWeight": 0.333333343,
              "tangentMode": 136
            },
            {
              "time": 0.566666663,
              "value": -9.983,
              "inWeight": 0.333333343,
              "outWeight": 0.333333343,
              "tangentMode": 136
            },
            {
              "time": 0.65,
              "value": -6.908,
              "inTangent": 41.5333366,
              "outTangent": 41.5333366,
              "inWeight": 0.333333343,
              "outWeight": 0.333333343,
              "tangentMode": 136
            },
            {
              "time": 0.716666639,
              "value": -3.753,
              "inWeight": 0.333333343,
              "outWeight": 0.333333343,
              "tangentMode": 136
            },
            {
              "time": 0.8,
              "value": -7.879,
              "inWeight": 0.333333343,
              "outWeight": 0.333333343,
              "tangentMode": 136
            },
            {
              "time": 1.05,
              "value": -3.801,
              "inWeight": 0.333333343,
              "outWeight": 0.333333343,
              "tangentMode": 136
            },
            {
              "time": 1.33333337,
              "value": -3.801,
              "inWeight": 0.333333343,
              "outWeight": 0.333333343,
              "tangentMode": 136
            },
            {
              "time": 1.41666663,
              "value": -3.801,
              "inWeight": 0.333333343,
              "outWeight": 0.333333343,
              "tangentMode": 136
            },
            {
              "time": 1.4666667,
              "value": -17.37,
              "inWeight": 0.333333343,
              "outWeight": 0.333333343,
              "tangentMode": 136
            },
            {
              "time": 1.51666665,
              "value": -17.37,
              "inWeight": 0.333333343,
              "outWeight": 0.333333343,
              "tangentMode": 136
            },
            {
              "time": 1.65,
              "value": -4.538,
              "inTangent": 35.93793,
              "outTangent": 35.93793,
              "inWeight": 0.333333343,
              "outWeight": 0.333333343,
              "tangentMode": 136
            },
            {
              "time": 2.0,
              "inWeight": 0.333333343,
              "outWeight": 0.333333343,
              "tangentMode": 136
            }
          ],
          "PreWrapMode": 8,
          "PostWrapMode": 8
        },
        "Transform.localEulerAnglesRaw.z": {
          "Keyframes": [
            {
              "inWeight": 0.333333343,
              "outWeight": 0.333333343,
              "tangentMode": 136
            },
            {
              "time": 0.316666663,
              "inWeight": 0.333333343,
              "outWeight": 0.333333343,
              "tangentMode": 136
            },
            {
              "time": 0.45,
              "inWeight": 0.333333343,
              "outWeight": 0.333333343,
              "tangentMode": 136
            },
            {
              "time": 0.566666663,
              "inWeight": 0.333333343,
              "outWeight": 0.333333343,
              "tangentMode": 136
            },
            {
              "time": 0.65,
              "inWeight": 0.333333343,
              "outWeight": 0.333333343,
              "tangentMode": 136
            },
            {
              "time": 0.716666639,
              "inWeight": 0.333333343,
              "outWeight": 0.333333343,
              "tangentMode": 136
            },
            {
              "time": 0.8,
              "inWeight": 0.333333343,
              "outWeight": 0.333333343,
              "tangentMode": 136
            },
            {
              "time": 1.05,
              "inWeight": 0.333333343,
              "outWeight": 0.333333343,
              "tangentMode": 136
            },
            {
              "time": 1.33333337,
              "inWeight": 0.333333343,
              "outWeight": 0.333333343,
              "tangentMode": 136
            },
            {
              "time": 1.41666663,
              "inWeight": 0.333333343,
              "outWeight": 0.333333343,
              "tangentMode": 136
            },
            {
              "time": 1.4666667,
              "inWeight": 0.333333343,
              "outWeight": 0.333333343,
              "tangentMode": 136
            },
            {
              "time": 1.51666665,
              "inWeight": 0.333333343,
              "outWeight": 0.333333343,
              "tangentMode": 136
            },
            {
              "time": 1.65,
              "inWeight": 0.333333343,
              "outWeight": 0.333333343,
              "tangentMode": 136
            },
            {
              "time": 2.0,
              "inWeight": 0.333333343,
              "outWeight": 0.333333343,
              "tangentMode": 136
            }
          ],
          "PreWrapMode": 8,
          "PostWrapMode": 8
        }
      },
      "DefaultValues": {
        "GameObject.m_IsActive": 1.0,
        "Transform.m_LocalScale.x": 1.0,
        "Transform.m_LocalScale.y": 1.0,
        "Transform.m_LocalScale.z": 1.0,
        "AnimatedPart.DataA": 0.0,
        "AnimatedPart.DataB": 0.0,
        "AnimatedPart.DataC": 0.0,
        "AnimatedPart.Tint.r": 1.0,
        "AnimatedPart.Tint.g": 1.0,
        "AnimatedPart.Tint.b": 1.0,
        "AnimatedPart.Tint.a": 1.0,
        "AnimatedPart.FlipX": 0.0,
        "AnimatedPart.FlipY": 0.0,
        "AnimatedPart.SplitDrawMode": 0.0,
        "AnimatedPart.FrameIndex": 0.0,
        "PawnBody.Direction": 1.0
      },
      "SweepPaths": []
    },
    {
      "ID": 19138,
      "Path": "BodyB",
      "CustomName": "BodyB",
      "Curves": {
        "Transform.m_LocalPosition.x": {
          "Keyframes": [
            {
              "value": 1.0,
              "inWeight": 0.333333343,
              "outWeight": 0.333333343,
              "tangentMode": 136
            },
            {
              "time": 0.316666663,
              "value": 0.961,
              "inWeight": 0.333333343,
              "outWeight": 0.333333343,
              "tangentMode": 136
            },
            {
              "time": 0.383333325,
              "value": 0.961,
              "inWeight": 0.333333343,
              "outWeight": 0.333333343,
              "tangentMode": 136
            },
            {
              "time": 0.45,
              "value": 0.985,
              "inTangent": 0.316363782,
              "outTangent": 0.316363782,
              "inWeight": 0.333333343,
              "outWeight": 0.333333343,
              "tangentMode": -16711936
            },
            {
              "time": 0.566666663,
              "value": 1.019,
              "inWeight": 0.333333343,
              "outWeight": 0.333333343,
              "tangentMode": 136
            },
            {
              "time": 0.716666639,
              "value": 0.929,
              "inWeight": 0.333333343,
              "outWeight": 0.333333343,
              "tangentMode": 136
            },
            {
              "time": 0.8,
              "value": 0.974,
              "inTangent": 0.346153468,
              "outTangent": 0.346153468,
              "inWeight": 0.333333343,
              "outWeight": 0.333333343,
              "tangentMode": 136
            },
            {
              "time": 0.933333337,
              "value": 1.004,
              "inWeight": 0.333333343,
              "outWeight": 0.333333343,
              "tangentMode": 136
            },
            {
              "time": 1.05,
              "value": 0.949,
              "inTangent": -0.539173,
              "outTangent": -0.539173,
              "inWeight": 0.333333343,
              "outWeight": 0.333333343,
              "tangentMode": 136
            },
            {
              "time": 1.18333328,
              "value": 0.8692067,
              "inTangent": -0.4023529,
              "outTangent": -0.4023529,
              "inWeight": 0.333333343,
              "outWeight": 0.333333343,
              "tangentMode": 136
            },
            {
              "time": 1.33333337,
              "value": 0.835,
              "inTangent": -0.442314625,
              "outTangent": -0.442314625,
              "inWeight": 0.333333343,
              "outWeight": 0.333333343,
              "tangentMode": 136
            },
            {
              "time": 1.41666663,
              "value": 0.766,
              "inWeight": 0.333333343,
              "outWeight": 0.333333343,
              "tangentMode": 136
            },
            {
              "time": 1.4666667,
              "value": 0.766,
              "inWeight": 0.333333343,
              "outWeight": 0.333333343,
              "tangentMode": 136
            },
            {
              "time": 1.51666665,
              "value": 0.834,
              "inTangent": 0.906667054,
              "outTangent": 0.906667054,
              "inWeight": 0.333333343,
              "outWeight": 0.333333343,
              "tangentMode": 136
            },
            {
              "time": 1.76666665,
              "value": 1.338,
              "inWeight": 0.333333343,
              "outWeight": 0.333333343,
              "tangentMode": 136
            }
          ],
          "PreWrapMode": 8,
          "PostWrapMode": 8
        },
        "Transform.m_LocalPosition.y": {
          "Keyframes": [
            {
              "inWeight": 0.333333343,
              "outWeight": 0.333333343,
              "tangentMode": 136
            },
            {
              "time": 0.316666663,
              "inWeight": 0.333333343,
              "outWeight": 0.333333343,
              "tangentMode": 136
            },
            {
              "time": 0.383333325,
              "inWeight": 0.333333343,
              "outWeight": 0.333333343,
              "tangentMode": 136
            },
            {
              "time": 0.45,
              "inWeight": 0.333333343,
              "outWeight": 0.333333343,
              "tangentMode": 136
            },
            {
              "time": 0.566666663,
              "inWeight": 0.333333343,
              "outWeight": 0.333333343,
              "tangentMode": 136
            },
            {
              "time": 0.716666639,
              "inWeight": 0.333333343,
              "outWeight": 0.333333343,
              "tangentMode": 136
            },
            {
              "time": 0.8,
              "inWeight": 0.333333343,
              "outWeight": 0.333333343,
              "tangentMode": 136
            },
            {
              "time": 0.933333337,
              "inWeight": 0.333333343,
              "outWeight": 0.333333343,
              "tangentMode": 136
            },
            {
              "time": 1.05,
              "inWeight": 0.333333343,
              "outWeight": 0.333333343,
              "tangentMode": 136
            },
            {
              "time": 1.18333328,
              "inWeight": 0.333333343,
              "outWeight": 0.333333343,
              "tangentMode": 136
            },
            {
              "time": 1.33333337,
              "inWeight": 0.333333343,
              "outWeight": 0.333333343,
              "tangentMode": 136
            },
            {
              "time": 1.41666663,
              "inWeight": 0.333333343,
              "outWeight": 0.333333343,
              "tangentMode": 136
            },
            {
              "time": 1.4666667,
              "inWeight": 0.333333343,
              "outWeight": 0.333333343,
              "tangentMode": 136
            },
            {
              "time": 1.51666665,
              "inWeight": 0.333333343,
              "outWeight": 0.333333343,
              "tangentMode": 136
            },
            {
              "time": 1.76666665,
              "inWeight": 0.333333343,
              "outWeight": 0.333333343,
              "tangentMode": 136
            }
          ],
          "PreWrapMode": 8,
          "PostWrapMode": 8
        },
        "Transform.m_LocalPosition.z": {
          "Keyframes": [
            {
              "inWeight": 0.333333343,
              "outWeight": 0.333333343,
              "tangentMode": 136
            },
            {
              "time": 0.316666663,
              "inWeight": 0.333333343,
              "outWeight": 0.333333343,
              "tangentMode": 136
            },
            {
              "time": 0.383333325,
              "inWeight": 0.333333343,
              "outWeight": 0.333333343,
              "tangentMode": 136
            },
            {
              "time": 0.45,
              "value": 0.034,
              "inWeight": 0.333333343,
              "outWeight": 0.333333343,
              "tangentMode": 136
            },
            {
              "time": 0.566666663,
              "value": 0.034,
              "inWeight": 0.333333343,
              "outWeight": 0.333333343,
              "tangentMode": 136
            },
            {
              "time": 0.716666639,
              "value": -0.008,
              "inWeight": 0.333333343,
              "outWeight": 0.333333343,
              "tangentMode": 136
            },
            {
              "time": 0.8,
              "value": 0.032,
              "inTangent": 0.0553844273,
              "outTangent": 0.0553844273,
              "inWeight": 0.333333343,
              "outWeight": 0.333333343,
              "tangentMode": 136
            },
            {
              "time": 0.933333337,
              "value": 0.0349999927,
              "inTangent": 0.04799987,
              "outTangent": 0.04799987,
              "inWeight": 0.333333343,
              "outWeight": 0.333333343,
              "tangentMode": 136
            },
            {
              "time": 1.05,
              "value": 0.046,
              "inTangent": 0.116000071,
              "outTangent": 0.116000071,
              "inWeight": 0.333333343,
              "outWeight": 0.333333343,
              "tangentMode": 136
            },
            {
              "time": 1.18333328,
              "value": 0.064,
              "inTangent": 0.112941146,
              "outTangent": 0.112941146,
              "inWeight": 0.333333343,
              "outWeight": 0.333333343,
              "tangentMode": 136
            },
            {
              "time": 1.33333337,
              "value": 0.078,
              "inWeight": 0.333333343,
              "outWeight": 0.333333343,
              "tangentMode": 136
            },
            {
              "time": 1.41666663,
              "value": 0.056,
              "inWeight": 0.333333343,
              "outWeight": 0.333333343,
              "tangentMode": 136
            },
            {
              "time": 1.4666667,
              "value": 0.056,
              "inWeight": 0.333333343,
              "outWeight": 0.333333343,
              "tangentMode": 136
            },
            {
              "time": 1.51666665,
              "value": 0.096,
              "inWeight": 0.333333343,
              "outWeight": 0.333333343,
              "tangentMode": 136
            },
            {
              "time": 1.76666665,
              "value": -0.224,
              "inWeight": 0.333333343,
              "outWeight": 0.333333343,
              "tangentMode": 136
            }
          ],
          "PreWrapMode": 8,
          "PostWrapMode": 8
        },
        "Transform.localEulerAnglesRaw.x": {
          "Keyframes": [
            {
              "time": 0.383333325,
              "inWeight": 0.333333343,
              "outWeight": 0.333333343,
              "tangentMode": 136
            },
            {
              "time": 0.45,
              "inWeight": 0.333333343,
              "outWeight": 0.333333343,
              "tangentMode": 136
            },
            {
              "time": 0.566666663,
              "inWeight": 0.333333343,
              "outWeight": 0.333333343,
              "tangentMode": 136
            },
            {
              "time": 0.716666639,
              "inWeight": 0.333333343,
              "outWeight": 0.333333343,
              "tangentMode": 136
            },
            {
              "time": 0.8,
              "inWeight": 0.333333343,
              "outWeight": 0.333333343,
              "tangentMode": 136
            },
            {
              "time": 0.933333337,
              "inWeight": 0.333333343,
              "outWeight": 0.333333343,
              "tangentMode": 136
            },
            {
              "time": 1.05,
              "inWeight": 0.333333343,
              "outWeight": 0.333333343,
              "tangentMode": 136
            },
            {
              "time": 1.18333328,
              "inWeight": 0.333333343,
              "outWeight": 0.333333343,
              "tangentMode": 136
            },
            {
              "time": 1.33333337,
              "inWeight": 0.333333343,
              "outWeight": 0.333333343,
              "tangentMode": 136
            },
            {
              "time": 1.41666663,
              "inWeight": 0.333333343,
              "outWeight": 0.333333343,
              "tangentMode": 136
            },
            {
              "time": 1.4666667,
              "inWeight": 0.333333343,
              "outWeight": 0.333333343,
              "tangentMode": 136
            },
            {
              "time": 1.51666665,
              "inWeight": 0.333333343,
              "outWeight": 0.333333343,
              "tangentMode": 136
            },
            {
              "time": 1.76666665,
              "inWeight": 0.333333343,
              "outWeight": 0.333333343,
              "tangentMode": 136
            }
          ],
          "PreWrapMode": 8,
          "PostWrapMode": 8
        },
        "Transform.localEulerAnglesRaw.y": {
          "Keyframes": [
            {
              "time": 0.383333325,
              "inWeight": 0.333333343,
              "outWeight": 0.333333343,
              "tangentMode": 136
            },
            {
              "time": 0.45,
              "value": -8.712,
              "inWeight": 0.333333343,
              "outWeight": 0.333333343,
              "tangentMode": 136
            },
            {
              "time": 0.566666663,
              "value": -8.712,
              "inWeight": 0.333333343,
              "outWeight": 0.333333343,
              "tangentMode": 136
            },
            {
              "time": 0.716666639,
              "value": 0.944,
              "inWeight": 0.333333343,
              "outWeight": 0.333333343,
              "tangentMode": 136
            },
            {
              "time": 0.8,
              "value": -8.601,
              "inWeight": 0.333333343,
              "outWeight": 0.333333343,
              "tangentMode": 136
            },
            {
              "time": 0.933333337,
              "value": -8.601,
              "inWeight": 0.333333343,
              "outWeight": 0.333333343,
              "tangentMode": 136
            },
            {
              "time": 1.05,
              "value": 5.912,
              "inTangent": -1.71465219E+38,
              "outTangent": 93.45203,
              "inWeight": 0.333333343,
              "outWeight": 0.333333343,
              "tangentMode": 136
            },
            {
              "time": 1.18333328,
              "value": 14.762,
              "inWeight": 0.333333343,
              "outWeight": 0.333333343,
              "tangentMode": 136
            },
            {
              "time": 1.33333337,
              "value": 6.107,
              "inTangent": -38.45142,
              "outTangent": -38.45142,
              "inWeight": 0.333333343,
              "outWeight": 0.333333343,
              "tangentMode": 136
            },
            {
              "time": 1.41666663,
              "value": 3.864,
              "inWeight": 0.333333343,
              "outWeight": 0.333333343,
              "tangentMode": 136
            },
            {
              "time": 1.4666667,
              "value": 3.864,
              "inWeight": 0.333333343,
              "outWeight": 0.333333343,
              "tangentMode": 136
            },
            {
              "time": 1.51666665,
              "value": 21.544,
              "inTangent": 235.733368,
              "outTangent": 235.733368,
              "inWeight": 0.333333343,
              "outWeight": 0.333333343,
              "tangentMode": 136
            },
            {
              "time": 1.76666665,
              "value": 85.238,
              "inWeight": 0.333333343,
              "outWeight": 0.333333343,
              "tangentMode": 136
            }
          ],
          "PreWrapMode": 8,
          "PostWrapMode": 8
        },
        "Transform.localEulerAnglesRaw.z": {
          "Keyframes": [
            {
              "time": 0.383333325,
              "inWeight": 0.333333343,
              "outWeight": 0.333333343,
              "tangentMode": 136
            },
            {
              "time": 0.45,
              "inWeight": 0.333333343,
              "outWeight": 0.333333343,
              "tangentMode": 136
            },
            {
              "time": 0.566666663,
              "inWeight": 0.333333343,
              "outWeight": 0.333333343,
              "tangentMode": 136
            },
            {
              "time": 0.716666639,
              "inWeight": 0.333333343,
              "outWeight": 0.333333343,
              "tangentMode": 136
            },
            {
              "time": 0.8,
              "inWeight": 0.333333343,
              "outWeight": 0.333333343,
              "tangentMode": 136
            },
            {
              "time": 0.933333337,
              "inWeight": 0.333333343,
              "outWeight": 0.333333343,
              "tangentMode": 136
            },
            {
              "time": 1.05,
              "inWeight": 0.333333343,
              "outWeight": 0.333333343,
              "tangentMode": 136
            },
            {
              "time": 1.18333328,
              "inWeight": 0.333333343,
              "outWeight": 0.333333343,
              "tangentMode": 136
            },
            {
              "time": 1.33333337,
              "inWeight": 0.333333343,
              "outWeight": 0.333333343,
              "tangentMode": 136
            },
            {
              "time": 1.41666663,
              "inWeight": 0.333333343,
              "outWeight": 0.333333343,
              "tangentMode": 136
            },
            {
              "time": 1.4666667,
              "inWeight": 0.333333343,
              "outWeight": 0.333333343,
              "tangentMode": 136
            },
            {
              "time": 1.51666665,
              "inWeight": 0.333333343,
              "outWeight": 0.333333343,
              "tangentMode": 136
            },
            {
              "time": 1.76666665,
              "inWeight": 0.333333343,
              "outWeight": 0.333333343,
              "tangentMode": 136
            }
          ],
          "PreWrapMode": 8,
          "PostWrapMode": 8
        },
        "PawnBody.Direction": {
          "Keyframes": [
            {
              "value": 3.0,
              "inTangent": "Infinity",
              "outTangent": "Infinity",
              "tangentMode": 103
            },
            {
              "time": 1.58333337,
              "inTangent": "Infinity",
              "outTangent": "Infinity",
              "tangentMode": 103
            },
            {
              "time": 1.7,
              "value": 1.0,
              "inTangent": "Infinity",
              "outTangent": "Infinity",
              "tangentMode": 103
            }
          ],
          "PreWrapMode": 8,
          "PostWrapMode": 8
        }
      },
      "DefaultValues": {
        "GameObject.m_IsActive": 1.0,
        "Transform.m_LocalScale.x": 1.0,
        "Transform.m_LocalScale.y": 1.0,
        "Transform.m_LocalScale.z": 1.0,
        "AnimatedPart.DataA": 0.0,
        "AnimatedPart.DataB": 0.0,
        "AnimatedPart.DataC": 0.0,
        "AnimatedPart.Tint.r": 1.0,
        "AnimatedPart.Tint.g": 1.0,
        "AnimatedPart.Tint.b": 1.0,
        "AnimatedPart.Tint.a": 1.0,
        "AnimatedPart.FlipX": 1.0,
        "AnimatedPart.FlipY": 0.0,
        "AnimatedPart.SplitDrawMode": 0.0,
        "AnimatedPart.FrameIndex": 0.0
      },
      "SweepPaths": []
    },
    {
      "ID": 19712,
      "Path": "PawnAHolding/HandB",
      "CustomName": "HandB",
      "ParentID": 19430,
      "Curves": {
        "GameObject.m_IsActive": {
          "Keyframes": [
            {
              "inTangent": "Infinity",
              "outTangent": "Infinity",
              "tangentMode": 103
            },
            {
              "time": 2.0,
              "inTangent": "Infinity",
              "outTangent": "Infinity",
              "tangentMode": 103
            }
          ],
          "PreWrapMode": 8,
          "PostWrapMode": 8
        }
      },
      "DefaultValues": {
        "Transform.m_LocalPosition.x": -0.146,
        "Transform.m_LocalPosition.y": -0.05,
        "Transform.m_LocalPosition.z": -0.011,
        "Transform.localEulerAnglesRaw.x": 0.0,
        "Transform.localEulerAnglesRaw.y": 0.0,
        "Transform.localEulerAnglesRaw.z": 0.0,
        "Transform.m_LocalScale.x": 0.175000012,
        "Transform.m_LocalScale.y": 0.175000012,
        "Transform.m_LocalScale.z": 0.175,
        "AnimatedPart.DataA": 0.0,
        "AnimatedPart.DataB": 0.0,
        "AnimatedPart.DataC": 0.0,
        "AnimatedPart.Tint.r": 0.8509804,
        "AnimatedPart.Tint.g": 0.7254902,
        "AnimatedPart.Tint.b": 0.5176471,
        "AnimatedPart.Tint.a": 1.0,
        "AnimatedPart.FlipX": 0.0,
        "AnimatedPart.FlipY": 0.0,
        "AnimatedPart.SplitDrawMode": 0.0,
        "AnimatedPart.FrameIndex": 0.0,
        "PawnBody.Direction": 0.0
      },
      "SweepPaths": []
    },
    {
      "ID": 19008,
      "Path": "BodyA/HeadA",
      "CustomName": "HeadA",
      "ParentID": 19452,
      "Curves": {},
      "DefaultValues": {
        "GameObject.m_IsActive": 1.0,
        "Transform.m_LocalPosition.x": 0.0,
        "Transform.m_LocalPosition.y": 0.05,
        "Transform.m_LocalPosition.z": 0.0,
        "Transform.localEulerAnglesRaw.x": 0.0,
        "Transform.localEulerAnglesRaw.y": 0.0,
        "Transform.localEulerAnglesRaw.z": 0.0,
        "Transform.m_LocalScale.x": 1.0,
        "Transform.m_LocalScale.y": 1.0,
        "Transform.m_LocalScale.z": 1.0,
        "AnimatedPart.DataA": 0.0,
        "AnimatedPart.DataB": 0.0,
        "AnimatedPart.DataC": 0.0,
        "AnimatedPart.Tint.r": 1.0,
        "AnimatedPart.Tint.g": 1.0,
        "AnimatedPart.Tint.b": 1.0,
        "AnimatedPart.Tint.a": 1.0,
        "AnimatedPart.FlipX": 0.0,
        "AnimatedPart.FlipY": 0.0,
        "AnimatedPart.SplitDrawMode": 0.0,
        "AnimatedPart.FrameIndex": 0.0,
        "PawnBody.Direction": 0.0
      },
      "SweepPaths": []
    },
    {
      "ID": 19412,
      "Path": "PawnAHolding/HandA",
      "CustomName": "HandA",
      "ParentID": 19430,
      "Curves": {},
      "DefaultValues": {
        "GameObject.m_IsActive": 1.0,
        "Transform.m_LocalPosition.x": 0.0,
        "Transform.m_LocalPosition.y": 0.05,
        "Transform.m_LocalPosition.z": 0.0,
        "Transform.localEulerAnglesRaw.x": 0.0,
        "Transform.localEulerAnglesRaw.y": 0.0,
        "Transform.localEulerAnglesRaw.z": 0.0,
        "Transform.m_LocalScale.x": 0.175000012,
        "Transform.m_LocalScale.y": 0.175000012,
        "Transform.m_LocalScale.z": 0.175,
        "AnimatedPart.DataA": 0.0,
        "AnimatedPart.DataB": 0.0,
        "AnimatedPart.DataC": 0.0,
        "AnimatedPart.Tint.r": 0.8509804,
        "AnimatedPart.Tint.g": 0.7254902,
        "AnimatedPart.Tint.b": 0.5176471,
        "AnimatedPart.Tint.a": 1.0,
        "AnimatedPart.FlipX": 0.0,
        "AnimatedPart.FlipY": 0.0,
        "AnimatedPart.SplitDrawMode": 0.0,
        "AnimatedPart.FrameIndex": 0.0,
        "PawnBody.Direction": 0.0
      },
      "SweepPaths": []
    },
    {
      "ID": 18920,
      "Path": "PawnAHolding/ItemA",
      "CustomName": "ItemA",
      "ParentID": 19430,
      "Curves": {},
      "DefaultValues": {
        "GameObject.m_IsActive": 1.0,
        "Transform.m_LocalPosition.x": 0.0,
        "Transform.m_LocalPosition.y": 0.0,
        "Transform.m_LocalPosition.z": 0.0,
        "Transform.localEulerAnglesRaw.x": 0.0,
        "Transform.localEulerAnglesRaw.y": 0.0,
        "Transform.localEulerAnglesRaw.z": 0.0,
        "Transform.m_LocalScale.x": 1.0,
        "Transform.m_LocalScale.y": 1.0,
        "Transform.m_LocalScale.z": 1.0,
        "AnimatedPart.DataA": 0.0,
        "AnimatedPart.DataB": 0.0,
        "AnimatedPart.DataC": 0.0,
        "AnimatedPart.Tint.r": 1.0,
        "AnimatedPart.Tint.g": 1.0,
        "AnimatedPart.Tint.b": 1.0,
        "AnimatedPart.Tint.a": 1.0,
        "AnimatedPart.FlipX": 0.0,
        "AnimatedPart.FlipY": 0.0,
        "AnimatedPart.SplitDrawMode": 0.0,
        "AnimatedPart.FrameIndex": 0.0,
        "PawnBody.Direction": 0.0
      },
      "SplitDrawPivotPartID": 19522,
      "SweepPaths": [
        [
          {
            "Time": 0.08333334,
            "X": -0.08881935,
            "Z": -0.215009555,
            "DX": 0.975768447,
            "DZ": -0.218805626
          },
          {
            "Time": 0.125,
            "X": 0.00762717426,
            "Z": -0.2221713,
            "DX": 0.9760444,
            "DZ": -0.217571244
          },
          {
            "Time": 0.166666657,
            "X": 0.103618518,
            "Z": -0.230348647,
            "DX": 0.9765309,
            "DZ": -0.215377226
          },
          {
            "Time": 0.225,
            "X": 0.194714531,
            "Z": -0.241752312,
            "DX": 0.9776627,
            "DZ": -0.210180148
          },
          {
            "Time": 0.325000018,
            "X": 0.285869956,
            "Z": -0.2647417,
            "DX": 0.9823432,
            "DZ": -0.187087953
          },
          {
            "Time": 0.345833361,
            "X": 0.3434916,
            "Z": -0.262179732,
            "DX": 0.9930027,
            "DZ": -0.118091427
          },
          {
            "Time": 0.3604167,
            "X": 0.3960557,
            "Z": -0.2591961,
            "DX": 0.9992281,
            "DZ": -0.03928279
          },
          {
            "Time": 0.3729167,
            "X": 0.445428371,
            "Z": -0.256173372,
            "DX": 0.999192953,
            "DZ": 0.0401670523
          },
          {
            "Time": 0.3854167,
            "X": 0.49596706,
            "Z": -0.2529611,
            "DX": 0.992288768,
            "DZ": 0.123947486
          },
          {
            "Time": 0.397916675,
            "X": 0.5450005,
            "Z": -0.249786735,
            "DX": 0.9786263,
            "DZ": 0.205646679
          },
          {
            "Time": 0.410416663,
            "X": 0.58985734,
            "Z": -0.2468777,
            "DX": 0.9602501,
            "DZ": 0.2791412
          },
          {
            "Time": 0.425,
            "X": 0.6333481,
            "Z": -0.24412255,
            "DX": 0.9378033,
            "DZ": 0.347166926
          },
          {
            "Time": 0.483333349,
            "X": 0.689992249,
            "Z": -0.242,
            "DX": 0.9172549,
            "DZ": 0.398300678
          },
          {
            "Time": 0.6041667,
            "X": 0.6011203,
            "Z": -0.28239882,
            "DX": 0.9276614,
            "DZ": 0.373422444
          },
          {
            "Time": 0.62500006,
            "X": 0.5027876,
            "Z": -0.3164801,
            "DX": 0.9388029,
            "DZ": 0.344454825
          },
          {
            "Time": 0.6500001,
            "X": 0.419999778,
            "Z": -0.337,
            "DX": 0.952625334,
            "DZ": 0.30414626
          },
          {
            "Time": 0.700000048,
            "X": 0.3615937,
            "Z": -0.335218757,
            "DX": 0.9706237,
            "DZ": 0.240602866
          },
          {
            "Time": 0.7395834,
            "X": 0.4238868,
            "Z": -0.297832757,
            "DX": 0.9552206,
            "DZ": 0.295894742
          },
          {
            "Time": 0.75,
            "X": 0.484072059,
            "Z": -0.266159952,
            "DX": 0.936819553,
            "DZ": 0.349812984
          },
          {
            "Time": 0.7604166,
            "X": 0.551026,
            "Z": -0.23109135,
            "DX": 0.912779331,
            "DZ": 0.408453017
          },
          {
            "Time": 0.770833254,
            "X": 0.616287768,
            "Z": -0.197001889,
            "DX": 0.8858172,
            "DZ": 0.4640343
          },
          {
            "Time": 0.783333242,
            "X": 0.680455565,
            "Z": -0.16354686,
            "DX": 0.8560105,
            "DZ": 0.5169585
          },
          {
            "Time": 0.9833333,
            "X": 0.607189,
            "Z": -0.202644274,
            "DX": 0.888617456,
            "DZ": 0.458649129
          },
          {
            "Time": 1.0041666,
            "X": 0.525824547,
            "Z": -0.242079854,
            "DX": 0.895627737,
            "DZ": 0.4448044
          },
          {
            "Time": 1.02916658,
            "X": 0.432603121,
            "Z": -0.280443,
            "DX": 0.903028369,
            "DZ": 0.429580927
          },
          {
            "Time": 1.07083333,
            "X": 0.343770653,
            "Z": -0.2909678,
            "DX": 0.9120817,
            "DZ": 0.4100085
          },
          {
            "Time": 1.1364584,
            "X": 0.287978977,
            "Z": -0.26002112,
            "DX": 0.8991623,
            "DZ": 0.437615335
          },
          {
            "Time": 1.15104175,
            "X": 0.276691169,
            "Z": -0.248570785,
            "DX": 0.863993764,
            "DZ": 0.5035025
          },
          {
            "Time": 1.16354179,
            "X": 0.264956027,
            "Z": -0.237561837,
            "DX": 0.8156292,
            "DZ": 0.578575
          },
          {
            "Time": 1.17395854,
            "X": 0.253045082,
            "Z": -0.2275824,
            "DX": 0.760782957,
            "DZ": 0.649006367
          },
          {
            "Time": 1.18229187,
            "X": 0.241750732,
            "Z": -0.219091922,
            "DX": 0.706817269,
            "DZ": 0.70739615
          },
          {
            "Time": 1.19062519,
            "X": 0.22902897,
            "Z": -0.209863737,
            "DX": 0.643851,
            "DZ": 0.7651509
          },
          {
            "Time": 1.19895852,
            "X": 0.215498969,
            "Z": -0.199505985,
            "DX": 0.572271168,
            "DZ": 0.8200644
          },
          {
            "Time": 1.20625019,
            "X": 0.203067869,
            "Z": -0.1896235,
            "DX": 0.5031985,
            "DZ": 0.8641709
          },
          {
            "Time": 1.21354175,
            "X": 0.190141514,
            "Z": -0.179076821,
            "DX": 0.428944945,
            "DZ": 0.903330743
          },
          {
            "Time": 1.2208333,
            "X": 0.176774457,
            "Z": -0.167961657,
            "DX": 0.3505267,
            "DZ": 0.9365528
          },
          {
            "Time": 1.22812486,
            "X": 0.16302146,
            "Z": -0.156373844,
            "DX": 0.269138753,
            "DZ": 0.963101447
          },
          {
            "Time": 1.23541641,
            "X": 0.148937285,
            "Z": -0.144409269,
            "DX": 0.186105132,
            "DZ": 0.9825298
          },
          {
            "Time": 1.242708,
            "X": 0.134576648,
            "Z": -0.132163778,
            "DX": 0.102821231,
            "DZ": 0.994699955
          },
          {
            "Time": 1.24999952,
            "X": 0.119994372,
            "Z": -0.119733244,
            "DX": 0.02069366,
            "DZ": 0.99978596
          },
          {
            "Time": 1.25833285,
            "X": 0.10312745,
            "Z": -0.105423078,
            "DX": -0.07001138,
            "DZ": 0.9975463
          },
          {
            "Time": 1.26666617,
            "X": 0.0861242563,
            "Z": -0.0911395252,
            "DX": -0.155563354,
            "DZ": 0.9878259
          },
          {
            "Time": 1.2749995,
            "X": 0.06906651,
            "Z": -0.07702567,
            "DX": -0.23433423,
            "DZ": 0.9721562
          },
          {
            "Time": 1.28541613,
            "X": 0.0477921963,
            "Z": -0.0598400533,
            "DX": -0.321242452,
            "DZ": 0.946997046
          },
          {
            "Time": 1.29583287,
            "X": 0.0267197937,
            "Z": -0.04342246,
            "DX": -0.39348948,
            "DZ": 0.9193292
          },
          {
            "Time": 1.30833292,
            "X": 0.00192460418,
            "Z": -0.02512905,
            "DX": -0.458912253,
            "DZ": 0.888481736
          },
          {
            "Time": 1.3333329,
            "X": -0.0449991673,
            "Z": 0.004999563,
            "DX": -0.5135715,
            "DZ": 0.8580469
          },
          {
            "Time": 1.383333,
            "X": -0.144157588,
            "Z": 0.0296581276,
            "DX": -0.5135715,
            "DZ": 0.858047068
          },
          {
            "Time": 1.42812467,
            "X": -0.07682805,
            "Z": 0.104344428,
            "DX": -0.5135715,
            "DZ": 0.858047068
          },
          {
            "Time": 1.43333292,
            "X": 0.0166217536,
            "Z": 0.133182868,
            "DX": -0.5135715,
            "DZ": 0.858047068
          },
          {
            "Time": 1.43749952,
            "X": 0.103474826,
            "Z": 0.158463,
            "DX": -0.5135715,
            "DZ": 0.858047068
          },
          {
            "Time": 1.44166613,
            "X": 0.195488036,
            "Z": 0.18437171,
            "DX": -0.5135715,
            "DZ": 0.858047068
          },
          {
            "Time": 1.44583273,
            "X": 0.287501872,
            "Z": 0.209676445,
            "DX": -0.5135715,
            "DZ": 0.858047068
          },
          {
            "Time": 1.45052016,
            "X": 0.384594142,
            "Z": 0.235887587,
            "DX": -0.5135715,
            "DZ": 0.858047068
          },
          {
            "Time": 1.45572853,
            "X": 0.4758836,
            "Z": 0.26015088,
            "DX": -0.5135715,
            "DZ": 0.858047068
          },
          {
            "Time": 1.46822858,
            "X": 0.567,
            "Z": 0.284,
            "DX": -0.5135715,
            "DZ": 0.858047068
          },
          {
            "Time": 1.55989516,
            "X": 0.615201,
            "Z": 0.256323844,
            "DX": -0.46531713,
            "DZ": 0.8851441
          },
          {
            "Time": 1.58072853,
            "X": 0.6587887,
            "Z": 0.229159772,
            "DX": -0.4154079,
            "DZ": 0.909635365
          },
          {
            "Time": 1.60156178,
            "X": 0.703492165,
            "Z": 0.198123425,
            "DX": -0.355188131,
            "DZ": 0.9347948
          },
          {
            "Time": 1.622395,
            "X": 0.7403854,
            "Z": 0.166984081,
            "DX": -0.2906382,
            "DZ": 0.956832945
          },
          {
            "Time": 1.647395,
            "X": 0.7617796,
            "Z": 0.134788185,
            "DX": -0.216875434,
            "DZ": 0.9761992
          },
          {
            "Time": 1.67656159,
            "X": 0.7539293,
            "Z": 0.102509551,
            "DX": -0.130491138,
            "DZ": 0.991449535
          },
          {
            "Time": 1.69739485,
            "X": 0.737378061,
            "Z": 0.07731798,
            "DX": -0.057222724,
            "DZ": 0.9983615
          },
          {
            "Time": 1.7182281,
            "X": 0.713200331,
            "Z": 0.0507845134,
            "DX": 0.0236097574,
            "DZ": 0.999721348
          },
          {
            "Time": 1.73437393,
            "X": 0.690009058,
            "Z": 0.0295719877,
            "DX": 0.09004825,
            "DZ": 0.9959374
          },
          {
            "Time": 1.74999881,
            "X": 0.6644627,
            "Z": 0.008711532,
            "DX": 0.156335235,
            "DZ": 0.987704039
          },
          {
            "Time": 1.76562381,
            "X": 0.6363946,
            "Z": -0.0122922957,
            "DX": 0.223502457,
            "DZ": 0.974703431
          },
          {
            "Time": 1.78020716,
            "X": 0.6083863,
            "Z": -0.0318648368,
            "DX": 0.286036,
            "DZ": 0.9582189
          },
          {
            "Time": 1.79479051,
            "X": 0.579066157,
            "Z": -0.05125618,
            "DX": 0.347539961,
            "DZ": 0.9376652
          },
          {
            "Time": 1.80937386,
            "X": 0.548861265,
            "Z": -0.07031861,
            "DX": 0.407201529,
            "DZ": 0.913338363
          },
          {
            "Time": 1.82499886,
            "X": 0.5160024,
            "Z": -0.09020981,
            "DX": 0.468236864,
            "DZ": 0.883603
          },
          {
            "Time": 1.84062386,
            "X": 0.483143479,
            "Z": -0.109372213,
            "DX": 0.5255047,
            "DZ": 0.850790739
          },
          {
            "Time": 1.85703015,
            "X": 0.449216276,
            "Z": -0.12850967,
            "DX": 0.5808603,
            "DZ": 0.8140032
          },
          {
            "Time": 1.87786341,
            "X": 0.407924116,
            "Z": -0.151034,
            "DX": 0.6432227,
            "DZ": 0.7656792
          },
          {
            "Time": 1.89869666,
            "X": 0.369791448,
            "Z": -0.171170056,
            "DX": 0.6960271,
            "DZ": 0.718015552
          },
          {
            "Time": 1.92369664,
            "X": 0.3299557,
            "Z": -0.191574425,
            "DX": 0.7463349,
            "DZ": 0.6655706
          },
          {
            "Time": 1.95650911,
            "X": 0.290902138,
            "Z": -0.210947931,
            "DX": 0.7908293,
            "DZ": 0.6120368
          }
        ]
      ]
    },
    {
      "ID": 19628,
      "Path": "BodyB/HeadB",
      "CustomName": "HeadB",
      "ParentID": 19138,
      "Curves": {},
      "DefaultValues": {
        "GameObject.m_IsActive": 1.0,
        "Transform.m_LocalPosition.x": 0.0,
        "Transform.m_LocalPosition.y": 0.05,
        "Transform.m_LocalPosition.z": 0.0,
        "Transform.localEulerAnglesRaw.x": 0.0,
        "Transform.localEulerAnglesRaw.y": 0.0,
        "Transform.localEulerAnglesRaw.z": 0.0,
        "Transform.m_LocalScale.x": 1.0,
        "Transform.m_LocalScale.y": 1.0,
        "Transform.m_LocalScale.z": 1.0,
        "AnimatedPart.DataA": 0.0,
        "AnimatedPart.DataB": 0.0,
        "AnimatedPart.DataC": 0.0,
        "AnimatedPart.Tint.r": 1.0,
        "AnimatedPart.Tint.g": 1.0,
        "AnimatedPart.Tint.b": 1.0,
        "AnimatedPart.Tint.a": 1.0,
        "AnimatedPart.FlipX": 1.0,
        "AnimatedPart.FlipY": 0.0,
        "AnimatedPart.SplitDrawMode": 0.0,
        "AnimatedPart.FrameIndex": 0.0,
        "PawnBody.Direction": 0.0
      },
      "SweepPaths": []
    },
    {
      "ID": 19198,
      "Path": "PawnBHolding",
      "Curves": {},
      "DefaultValues": {
        "GameObject.m_IsActive": 0.0,
        "Transform.m_LocalPosition.x": 1.0,
        "Transform.m_LocalPosition.y": 0.2,
        "Transform.m_LocalPosition.z": 0.0,
        "Transform.localEulerAnglesRaw.x": 0.0,
        "Transform.localEulerAnglesRaw.y": 0.0,
        "Transform.localEulerAnglesRaw.z": 0.0,
        "Transform.m_LocalScale.x": 1.0,
        "Transform.m_LocalScale.y": 1.0,
        "Transform.m_LocalScale.z": 1.0,
        "AnimatedPart.DataA": 0.0,
        "AnimatedPart.DataB": 0.0,
        "AnimatedPart.DataC": 0.0,
        "AnimatedPart.Tint.r": 0.0,
        "AnimatedPart.Tint.g": 0.0,
        "AnimatedPart.Tint.b": 0.0,
        "AnimatedPart.Tint.a": 0.0,
        "AnimatedPart.FlipX": 0.0,
        "AnimatedPart.FlipY": 0.0,
        "AnimatedPart.SplitDrawMode": 0.0,
        "AnimatedPart.FrameIndex": 0.0,
        "PawnBody.Direction": 0.0
      },
      "SweepPaths": []
    },
    {
      "ID": 19440,
      "Path": "PawnBHolding/HandA",
      "CustomName": "HandA2",
      "ParentID": 19198,
      "Curves": {},
      "DefaultValues": {
        "GameObject.m_IsActive": 1.0,
        "Transform.m_LocalPosition.x": 0.0,
        "Transform.m_LocalPosition.y": 0.05,
        "Transform.m_LocalPosition.z": 0.0,
        "Transform.localEulerAnglesRaw.x": 0.0,
        "Transform.localEulerAnglesRaw.y": 0.0,
        "Transform.localEulerAnglesRaw.z": 0.0,
        "Transform.m_LocalScale.x": 0.175,
        "Transform.m_LocalScale.y": 0.175000012,
        "Transform.m_LocalScale.z": 0.175,
        "AnimatedPart.DataA": 0.0,
        "AnimatedPart.DataB": 0.0,
        "AnimatedPart.DataC": 0.0,
        "AnimatedPart.Tint.r": 0.8509804,
        "AnimatedPart.Tint.g": 0.7254902,
        "AnimatedPart.Tint.b": 0.5176471,
        "AnimatedPart.Tint.a": 1.0,
        "AnimatedPart.FlipX": 0.0,
        "AnimatedPart.FlipY": 0.0,
        "AnimatedPart.SplitDrawMode": 0.0,
        "AnimatedPart.FrameIndex": 0.0,
        "PawnBody.Direction": 0.0
      },
      "SweepPaths": []
    },
    {
      "ID": 19180,
      "Path": "PawnBHolding/HandB",
      "CustomName": "HandB2",
      "ParentID": 19198,
      "Curves": {},
      "DefaultValues": {
        "GameObject.m_IsActive": 1.0,
        "Transform.m_LocalPosition.x": 0.146,
        "Transform.m_LocalPosition.y": 0.0,
        "Transform.m_LocalPosition.z": -0.011,
        "Transform.localEulerAnglesRaw.x": 0.0,
        "Transform.localEulerAnglesRaw.y": 0.0,
        "Transform.localEulerAnglesRaw.z": 0.0,
        "Transform.m_LocalScale.x": 0.175000012,
        "Transform.m_LocalScale.y": 0.175000012,
        "Transform.m_LocalScale.z": 0.175,
        "AnimatedPart.DataA": 0.0,
        "AnimatedPart.DataB": 0.0,
        "AnimatedPart.DataC": 0.0,
        "AnimatedPart.Tint.r": 0.8509804,
        "AnimatedPart.Tint.g": 0.7254902,
        "AnimatedPart.Tint.b": 0.5176471,
        "AnimatedPart.Tint.a": 1.0,
        "AnimatedPart.FlipX": 0.0,
        "AnimatedPart.FlipY": 0.0,
        "AnimatedPart.SplitDrawMode": 0.0,
        "AnimatedPart.FrameIndex": 0.0,
        "PawnBody.Direction": 0.0
      },
      "SweepPaths": []
    },
    {
      "ID": 19552,
      "Path": "PawnBHolding/ItemB",
      "CustomName": "ItemB",
      "ParentID": 19198,
      "Curves": {},
      "DefaultValues": {
        "GameObject.m_IsActive": 1.0,
        "Transform.m_LocalPosition.x": 0.0,
        "Transform.m_LocalPosition.y": 0.0,
        "Transform.m_LocalPosition.z": 0.0,
        "Transform.localEulerAnglesRaw.x": 0.0,
        "Transform.localEulerAnglesRaw.y": 0.0,
        "Transform.localEulerAnglesRaw.z": 0.0,
        "Transform.m_LocalScale.x": 1.0,
        "Transform.m_LocalScale.y": 1.0,
        "Transform.m_LocalScale.z": 1.0,
        "AnimatedPart.DataA": 0.0,
        "AnimatedPart.DataB": 0.0,
        "AnimatedPart.DataC": 0.0,
        "AnimatedPart.Tint.r": 1.0,
        "AnimatedPart.Tint.g": 1.0,
        "AnimatedPart.Tint.b": 1.0,
        "AnimatedPart.Tint.a": 1.0,
        "AnimatedPart.FlipX": 1.0,
        "AnimatedPart.FlipY": 0.0,
        "AnimatedPart.SplitDrawMode": 0.0,
        "AnimatedPart.FrameIndex": 0.0,
        "PawnBody.Direction": 0.0
      },
      "SweepPaths": [
        []
      ]
    },
    {
      "ID": 19424,
      "Path": "HandGrabSparks",
      "TexturePath": "AAM/HandGrabSparks",
      "Curves": {},
      "DefaultValues": {
        "GameObject.m_IsActive": 0.0,
        "Transform.m_LocalPosition.x": 0.0,
        "Transform.m_LocalPosition.y": 0.0,
        "Transform.m_LocalPosition.z": 0.0,
        "Transform.localEulerAnglesRaw.x": 0.0,
        "Transform.localEulerAnglesRaw.y": 0.0,
        "Transform.localEulerAnglesRaw.z": 0.0,
        "Transform.m_LocalScale.x": 1.0,
        "Transform.m_LocalScale.y": 1.0,
        "Transform.m_LocalScale.z": 1.0,
        "AnimatedPart.DataA": 0.0,
        "AnimatedPart.DataB": 0.0,
        "AnimatedPart.DataC": 0.0,
        "AnimatedPart.Tint.r": 1.0,
        "AnimatedPart.Tint.g": 1.0,
        "AnimatedPart.Tint.b": 1.0,
        "AnimatedPart.Tint.a": 1.0,
        "AnimatedPart.FlipX": 0.0,
        "AnimatedPart.FlipY": 0.0,
        "AnimatedPart.SplitDrawMode": 0.0,
        "AnimatedPart.FrameIndex": 0.0,
        "PawnBody.Direction": 0.0
      },
      "SweepPaths": []
    },
    {
      "ID": 19522,
      "Path": "WeaponACutoff",
      "Curves": {},
      "DefaultValues": {
        "GameObject.m_IsActive": 1.0,
        "Transform.m_LocalPosition.x": 0.0,
        "Transform.m_LocalPosition.y": 0.0,
        "Transform.m_LocalPosition.z": 0.0,
        "Transform.localEulerAnglesRaw.x": 0.0,
        "Transform.localEulerAnglesRaw.y": 0.0,
        "Transform.localEulerAnglesRaw.z": 0.0,
        "Transform.m_LocalScale.x": 1.0,
        "Transform.m_LocalScale.y": 1.0,
        "Transform.m_LocalScale.z": 1.0,
        "AnimatedPart.DataA": 0.0,
        "AnimatedPart.DataB": 0.0,
        "AnimatedPart.DataC": 0.0,
        "AnimatedPart.Tint.r": 1.0,
        "AnimatedPart.Tint.g": 1.0,
        "AnimatedPart.Tint.b": 1.0,
        "AnimatedPart.Tint.a": 1.0,
        "AnimatedPart.FlipX": 0.0,
        "AnimatedPart.FlipY": 0.0,
        "AnimatedPart.SplitDrawMode": 0.0,
        "AnimatedPart.FrameIndex": 0.0,
        "PawnBody.Direction": 0.0
      },
      "SweepPaths": []
    }
  ]
}